Workbook

Sheet Dados Norteadores
A2: Projeto - Programação Linear e Aplicações | Q2: Data dos Dados
A3: Dados Norteadores Reais da Empresa "Hot Flowers Ind.Com. Acess Adultos LTDA | Q3: 01/01/2024 à 01/01/2025
B5: Quantidade de Vendas/ano | F5: Informações Financeiras de Créditos | J5: Dados Técnicos e Financeiros dos Produtos
B6: Grupo (0401) - Linha Convencional Macica | C6: Quantidade / ano | D6: Média/mês | F6: Despesas | G6: Valor / mês | H6: Valor / Trimestre | J6: Produto | K6: Custo unitário (R$) | L6: Preço de venda (R$) | M6: Lucro Unitário (R$) | N6: Custo/trimestre | O6: Receita/trimestre | P6: Receita/ano | Q6: Lucro líquido total / ano
B7: Protese Macica Natural 16x4 | C7: 2313 | D7: =C7/12 -> 192.75 | F7: Energia | G7: 3437.31 | H7: =G7*3 -> 10311.93 | J7: Protese Macica Natural 16x4 | K7: 16.25 | L7: 42 | M7: =L7-K7 -> 25.75 | N7: =((K7*D7)*3)+H7+H8 -> 32425.478 | O7: =(D7*L7)*3 -> 24286.5 | P7: =C7*L7 -> 97146 | Q7: =(M7*C7)-(G7+G8)*12 -> -32555.91
B8: Grupo (0402) - Linha Convencional Vibro I | F8: Gás | G8: =50867.94/12 -> 4238.995 | H8: =G8*3 -> 12716.985 | J8: Protese Vibro Int Natural 16x4 | K8: 28.31 | L8: 85 | M8: =L8-K8 -> 56.69 | N8: =((K8*D9)*3)+H7+H8 -> 29441.13 | O8: =(L8*D9)*3 -> 19252.5 | P8: =C9*L8 -> 77010 | Q8: =(M8*C9)-(G7+G8)*12 -> -40754.52
B9: Protese Vibro Int Natural 16x4 | C9: 906 | D9: =C9/12 -> 75.5 | J9: Protese Fogo da Paixão Display | K9: 16.75 | L9: 48 | M9: =L9-K9 -> 31.25 | N9: =((K9*D11)*3)+H7+H8 -> 78421.165 | O9: =(L9*D11)*3 -> 158736 | P9: =C11*L9 -> 634944 | Q9: =(M9*C11)-((G7+G8)*12) -> 321259.34
B10: Grupo (0409) - Linha Protese Fogo da Paixão
B11: Protese Fogo da Paixão Display | C11: 13228 | D11: =C11/12 -> 1102.3333 | F11: Produtividade (por unidade/por hora) | J11: Recursos Disponíveis (Restrições) | O11: Total Prejuízo
F12: Produto | G12: Horas por unidade | H12: Unidades/horas | J12: Recurso | K12: Limite Disponível | L12: Unidade | O12: =SUM(Q7:Q8) -> -73310.43
B13: Informações sobre os produtos | F13: Protese Macica Natural 16x4 | G13: =0.08333*60 -> 4.9998 | H13: 12 | J13: Horas de Produção disponível | K13: =((SUM(G13:G14))*(SUM(D7,D9)))*0.15+((SUM(G13:G14))*(SUM(D7,D9))) -> 5244.2258 | L13: h/mês
B14: Produto | C14: Insumo | D14: Total unitário | F14: Protese Vibro Int Natural 16x4 | G14: =0.2*60 -> 12 | H14: 5 | J14: Capital de Produção | K14: 1200000 | L14: mês
B15: Protese Macica Natural 16x4 | C15: Silicone (0,2212kg x R$48,42/kg | D15: 10.71 | F15: Protese Fogo da Paixão Display | G15: =0.08333*60 -> 4.9998 | H15: 12 | J15: Capacidade de Armazenamento | K15: =3000*12 -> 36000 | L15: un/Ano
C16: Pigmento | D16: 1.63
C17: Embalagem (Blister) | D17: 0.22
C18: Amortização Molde | D18: 0.16
C19: Mão de Obra | D19: 1.42
C20: Soma antes overhead | D20: =SUM(D15:D19) -> 14.14
C21: overhead 15% | D21: =0.15*D20 -> 2.121
C22: Total unitário | D22: =SUM(D20:D21) -> 16.261
B23: Protese Vibro Int Natural 16x4 | C23: Silicone | D23: 10.71
C24: Pigmento | D24: 1.63
C25: Embalagem (Blister) | D25: 0.22
C26: Motor Vibratório | D26: 2.15
C27: Baterias (2x AA) | D27: 6.35
C28: Amortização Molde | D28: 0.16
C29: Mão de Obra | D29: 3.4
C30: Soma antes overhead | D30: =SUM(D23:D29) -> 24.62
C31: overhead 15% | D31: =0.15*D30 -> 3.693
C32: Total unitário | D32: =SUM(D30:D31) -> 28.313
B33: Protese Vibro Int Natural 16x4 | C33: Silicone | D33: 10.71
C34: Pigmento | D34: 1.63
C35: Embalagem Display (US$0,12 = R$0,65) | D35: 0.65
C36: Amortização Molde | D36: 0.16
C37: Mão de Obra | D37: 1.42
C38: Soma antes overhead | D38: =SUM(D33:D37) -> 14.57
C39: overhead 15% | D39: =0.15*D38 -> 2.1855
C40: Total unitário | D40: =SUM(D38:D39) -> 16.7555

Sheet Dashboard

Sheet Análise I
B2: Tabela de Dados
B3: Produto | C3: Quantidade vendas/Ano | D3: preço venda (R$) | E3: Custo Unitário (R$) | F3: Lucro Unitário (R$) | G3: Capital de Produção / Mês | H3: Horas/un | I3: Custo Total de Produção | J3: Lucro Anual | K3: Horas Usadas / Ano | L3: Horas disponiveis / Ano
B4: Protese Macica Natural 16x4 | C4: ='Dados Norteadores'!C7 -> 2313 | D4: ='Dados Norteadores'!L7 -> 42 | E4: {='Dados Norteadores'!K7:K8} -> 16.25 | F4: {='Dados Norteadores'!M7:M8} -> 25.75 | G4: ='Dados Norteadores'!K14 -> 1200000 | H4: {='Dados Norteadores'!G13:G14} -> 4.9998 | I4: =E4*C4 -> 37586.25 | J4: {='Dados Norteadores'!Q7:Q8} -> -32555.91 | K4: =((SUM(_xlfn.ANCHORARRAY(H4)))*(SUM(C4:C5))) -> 54722.356 | L4: ='Dados Norteadores'!K13*12 -> 62930.71
B5: Protese Vibro Int Natural 16x4 | C5: ='Dados Norteadores'!C9 -> 906 | D5: ='Dados Norteadores'!L8 -> 85 | E5: 28.31 | F5: 56.69 | H5: 12 | I5: =E5*C5 -> 25648.86 | J5: -40754.52
B8: Resumo (Restrições) | C8: Variáveis de Decisão (X, Y) | E8: Resultados Esperados (Z)
B9: 1 - Lucro Total / Ano | C9: Protese Macica Natural 16x4 | D9: Protese Vibro Int Natural 16x4 | E9: =B10 -> 110920.89 | G9: Total Prejuízo | H9: Resultados
B10: =SUM(C10:D10) -> 110920.89 | C10: 59559.75 | D10: 51361.14 | G10: =SUM(_xlfn.ANCHORARRAY(J4)) -> -73310.43 | H10: =E9 -> 110920.89
B11: 2 - Restrição de Capacidade Produtiva em Horas
B12: =(0.1941667*C10)+(0.21167*D10) -> 22436.133
B13: 3 - Restrição de Capital
B14: =(0.631068*C10)+(0.49947*D10) -> 63239.601
B15: 4 - Restrição de Demanda Máxima
B16: =(C4*F4) -> 59559.75
B17: =C5*F5 -> 51361.14

Sheet Relatório de Sensibilidade 1
A1: Microsoft Excel 16.0 Relatório de Sensibilidade
A2: Planilha: [Projeto PLA - Hotflowers.xlsx]Análise I
A3: Relatório Criado: 05/11/2025 21:05:45
A6: Células Variáveis
D7: Final | E7: Reduzido | F7: Objetivo | G7: Permitido | H7: Permitido
B8: Célula | C8: Nome | D8: Valor | E8: Custo | F8: Coeficiente | G8: Aumentar | H8: Reduzir
B9: $B$13 | C9: Protese Macica Natural 16x4 | D9: 59559.75 | E9: 1 | F9: 1 | G9: 1e+30 | H9: 1
B10: $C$13 | C10: Protese Vibro Int Natural 16x4 | D10: 51361.14 | E10: 1 | F10: 1 | G10: 1e+30 | H10: 1
A12: Restrições
D13: Final | E13: Sombra | F13: Restrição | G13: Permitido | H13: Permitido
B14: Célula | C14: Nome | D14: Valor | E14: Preço | F14: Lateral R.H. | G14: Aumentar | H14: Reduzir
B15: $G$9 | C15: 2 - Restrição de Horas | D15: 22436.13 | E15: 0 | F15: 62930.71 | G15: 1e+30 | H15: 40494.577
B16: $H$9 | C16: 3 - Restrição de Capital | D16: 63239.6 | E16: 0 | F16: 1200000 | G16: 1e+30 | H16: 1136760.4
